dctorch/functional.py
dctorch-0.1.1.dist-info/LICENSE
dctorch-0.1.1.dist-info/METADATA
dctorch-0.1.1.dist-info/WHEEL
dctorch-0.1.1.dist-info/RECORD
